snaptec_resolver/__init__.py
snaptec_resolver/constants/__init__.py
snaptec_resolver/constants/constants.py
snaptec_resolver/data/__init__.py
snaptec_resolver/src/__init__.py
snaptec_resolver/src/databases/__init__.py
snaptec_resolver/src/databases/mysql_handler.py
snaptec_resolver/src/databases/sql_reader.py
snaptec_resolver/src/migrations/__init__.py
snaptec_resolver/src/utilities/__init__.py
snaptec_resolver/src/utilities/singleton.py
snaptec_resolver/src/utils/__init__.py
snaptec_resolver/src/utils/base_mysql_executor_resolver.py
snaptec_resolver/src/utils/base_sql_executor_resolver.py
snaptec_resolver/src/utils/merge_graphql_schemas.py
snaptec_resolver-0.1.2.dist-info/METADATA
snaptec_resolver-0.1.2.dist-info/WHEEL
snaptec_resolver-0.1.2.dist-info/top_level.txt
snaptec_resolver-0.1.2.dist-info/RECORD
