Metadata-Version: 2.1
Name: snaptec_resolver
Version: 0.1.2
Summary: Library supports
Author: Trung
Author-email: trung.dinh@snaptec.co
Classifier: Programming Language :: Python :: 3
Classifier: License :: OSI Approved :: MIT License
Classifier: Operating System :: OS Independent
Requires-Python: >=3.10
Requires-Dist: pymysql ==1.1.0
Requires-Dist: sshtunnel ==0.4.0
Requires-Dist: boto3 ==1.34.135
Requires-Dist: jinja2 ==3.1.4
